[
  {"LiveFrom": "01/01/2017", "CaseTypeID": "WillLodgement", "ID": "createWillLodgment", "Name": "Create a will lodgement", "Description": "Create a will lodgement", "DisplayOrder": 1, "PostConditionState": "WillLodgementCreated", "SecurityClassification": "Public", "ShowSummary": "Y", "EndButtonLabel": "Save and continue"},
  {
    "LiveFrom": "01/01/2017",
    "CaseTypeID": "WillLodgement",
    "ID": "matchApplication",
    "Name": "Match application",
    "Description": "Match application",
    "DisplayOrder": 2,
    "PreConditionState(s)": "WillLodgementCreated",
    "PostConditionState": "WillLodged",
    "CallBackURLAboutToStartEvent": "http://${CCD_DEF_CASE_SERVICE_BASE_URL}/case-matching/search-from-will-lodgement-flow",
    "CallBackURLAboutToSubmitEvent": "http://${CCD_DEF_CASE_SERVICE_BASE_URL}/case-matching/import-legacy-from-will-lodgement-flow",
    "RetriesTimeoutURLAboutToSubmitEvent": "5",
    "SecurityClassification": "Public",
    "ShowSummary": "Y"
  },
  {"LiveFrom": "01/01/2017", "CaseTypeID": "WillLodgement", "ID": "withdrawWill", "Name": "Withdraw will", "Description": "Withdraw will", "DisplayOrder": 3, "PreConditionState(s)": "WillLodged", "PostConditionState": "WillWithdrawn", "SecurityClassification": "Public", "ShowSummary": "Y"},
  {"LiveFrom": "01/01/2017", "CaseTypeID": "WillLodgement", "ID": "amendWilLodgement", "Name": "Amend will lodgement", "Description": "Amend will lodgement", "DisplayOrder": 3, "PreConditionState(s)": "*", "PostConditionState": "*", "SecurityClassification": "Public", "ShowSummary": "Y"},
  {"LiveFrom": "01/01/2017", "CaseTypeID": "WillLodgement", "ID": "uploadDocument", "Name": "Upload document", "Description": "Upload document", "DisplayOrder": 4, "PreConditionState(s)": "*", "PostConditionState": "*", "SecurityClassification": "Public", "ShowSummary": "N"},
  {"LiveFrom": "01/01/2017", "CaseTypeID": "WillLodgement", "ID": "addComment", "Name": "Add comment", "Description": "Add comment", "DisplayOrder": 5, "PreConditionState(s)": "*", "PostConditionState": "*", "SecurityClassification": "Public", "ShowSummary": "N"},
  {"LiveFrom": "01/01/2017", "CaseTypeID": "WillLodgement", "ID": "generateDepositReceipt", "Name": "Generate deposit receipt", "Description": "Generate deposit receipt", "DisplayOrder": 6, "PreConditionState(s)": "*", "PostConditionState": "*", "CallBackURLAboutToSubmitEvent": "http://${CCD_DEF_CASE_SERVICE_BASE_URL}/document/generate-deposit-receipt", "SecurityClassification": "Public", "ShowSummary": "N"},
  {"LiveFrom": "01/01/2017", "CaseTypeID": "WillLodgement", "ID": "importWill", "Name": "Import a wil lodgement", "Description": "Import a wil lodgement", "DisplayOrder": 7, "PostConditionState": "WillImported", "SecurityClassification": "Public", "ShowSummary": "N"},
  {"LiveFrom": "01/01/2017", "CaseTypeID": "WillLodgement", "ID": "amendWilForImport", "Name": "Amend will for import", "Description": "Amend will for import", "DisplayOrder": 8, "PreConditionState(s)": "WillImported", "PostConditionState": "WillLodgementCreated", "SecurityClassification": "Public", "ShowSummary": "N"}
]