[
  {"CaseTypeID": "GrantOfRepresentation", "CaseFieldID": "caseNameHmctsInternal", "UserRole": "caseworker-probate-issuer", "CRUD": "CRUD"},
  {"CaseTypeID": "GrantOfRepresentation", "CaseFieldID": "caseNameHmctsInternal", "UserRole": "caseworker-probate-caseadmin", "CRUD": "CRUD"},
  {"CaseTypeID": "GrantOfRepresentation", "CaseFieldID": "caseNameHmctsInternal", "UserRole": "caseworker-probate-caseofficer", "CRUD": "CRUD"},
  {"CaseTypeID": "GrantOfRepresentation", "CaseFieldID": "caseNameHmctsInternal", "UserRole": "caseworker-probate-registrar", "CRUD": "CRUD"},
  {"CaseTypeID": "GrantOfRepresentation", "CaseFieldID": "caseNameHmctsInternal", "UserRole": "caseworker-probate-superuser", "CRUD": "CRUD"},
  {"CaseTypeID": "GrantOfRepresentation", "CaseFieldID": "caseNameHmctsInternal", "UserRole": "caseworker-probate-scheduler", "CRUD": "CRUD"},
  {"CaseTypeID": "GrantOfRepresentation", "CaseFieldID": "caseNameHmctsInternal", "UserRole": "caseworker-probate-systemupdate", "CRUD": "CRU"},
  {"CaseTypeID": "GrantOfRepresentation", "CaseFieldID": "caseNameHmctsInternal", "UserRole": "caseworker-probate-rparobot", "CRUD": "CRUD"}
]
